{"cities": [{"city_name": "乌鲁木齐市", "city_code": "650100000000"}, {"city_name": "克拉玛依市", "city_code": "650200000000"}, {"city_name": "吐鲁番市", "city_code": "650400000000"}, {"city_name": "哈密市", "city_code": "650500000000"}, {"city_name": "昌吉回族自治州", "city_code": "652300000000"}, {"city_name": "博尔塔拉蒙古自治州", "city_code": "652700000000"}, {"city_name": "巴音郭楞蒙古自治州", "city_code": "652800000000"}, {"city_name": "阿克苏地区", "city_code": "652900000000"}, {"city_name": "克孜勒苏柯尔克孜自治州", "city_code": "653000000000"}, {"city_name": "喀什地区", "city_code": "653100000000"}, {"city_name": "和田地区", "city_code": "653200000000"}, {"city_name": "伊犁哈萨克自治州", "city_code": "654000000000"}, {"city_name": "塔城地区", "city_code": "654200000000"}, {"city_name": "阿勒泰地区", "city_code": "654300000000"}, {"city_name": "自治区直辖县级行政区划", "city_code": "659000000000"}]}