{"districts": [{"district_name": "市辖区", "district_code": "440701000000"}, {"district_name": "蓬江区", "district_code": "440703000000"}, {"district_name": "江海区", "district_code": "440704000000"}, {"district_name": "新会区", "district_code": "440705000000"}, {"district_name": "台山市", "district_code": "440781000000"}, {"district_name": "开平市", "district_code": "440783000000"}, {"district_name": "鹤山市", "district_code": "440784000000"}, {"district_name": "恩平市", "district_code": "440785000000"}], "city_name": "江门市", "city_code": "440700000000"}