{"districts": [{"district_name": "市辖区", "district_code": "510501000000"}, {"district_name": "江阳区", "district_code": "510502000000"}, {"district_name": "纳溪区", "district_code": "510503000000"}, {"district_name": "龙马潭区", "district_code": "510504000000"}, {"district_name": "泸县", "district_code": "510521000000"}, {"district_name": "合江县", "district_code": "510522000000"}, {"district_name": "叙永县", "district_code": "510524000000"}, {"district_name": "古蔺县", "district_code": "510525000000"}], "city_name": "泸州市", "city_code": "510500000000"}